interpreto/__init__.py
interpreto/typing.py
interpreto/_vendor/overcomplete/VENDORED_FROM
interpreto/_vendor/overcomplete/__init__.py
interpreto/_vendor/overcomplete/_sync_overcomplete.py
interpreto/_vendor/overcomplete/base.py
interpreto/_vendor/overcomplete/data.py
interpreto/_vendor/overcomplete/metrics.py
interpreto/_vendor/overcomplete/overcomplete.patch
interpreto/_vendor/overcomplete/optimization/__init__.py
interpreto/_vendor/overcomplete/optimization/archetypal_analysis.py
interpreto/_vendor/overcomplete/optimization/base.py
interpreto/_vendor/overcomplete/optimization/convex_nmf.py
interpreto/_vendor/overcomplete/optimization/nmf.py
interpreto/_vendor/overcomplete/optimization/semi_nmf.py
interpreto/_vendor/overcomplete/optimization/sklearn_wrappers.py
interpreto/_vendor/overcomplete/optimization/utils.py
interpreto/_vendor/overcomplete/sae/__init__.py
interpreto/_vendor/overcomplete/sae/archetypal_dictionary.py
interpreto/_vendor/overcomplete/sae/base.py
interpreto/_vendor/overcomplete/sae/batchtopk_sae.py
interpreto/_vendor/overcomplete/sae/dictionary.py
interpreto/_vendor/overcomplete/sae/factory.py
interpreto/_vendor/overcomplete/sae/jump_sae.py
interpreto/_vendor/overcomplete/sae/kernels.py
interpreto/_vendor/overcomplete/sae/losses.py
interpreto/_vendor/overcomplete/sae/modules.py
interpreto/_vendor/overcomplete/sae/mp_sae.py
interpreto/_vendor/overcomplete/sae/omp_sae.py
interpreto/_vendor/overcomplete/sae/optimizer.py
interpreto/_vendor/overcomplete/sae/qsae.py
interpreto/_vendor/overcomplete/sae/rasae.py
interpreto/_vendor/overcomplete/sae/topk_sae.py
interpreto/_vendor/overcomplete/sae/trackers.py
interpreto/_vendor/overcomplete/sae/train.py
interpreto/attributions/__init__.py
interpreto/attributions/base.py
interpreto/attributions/aggregations/__init__.py
interpreto/attributions/aggregations/base.py
interpreto/attributions/aggregations/linear_regression_aggregation.py
interpreto/attributions/aggregations/sobol_aggregation.py
interpreto-0.4.15.dist-info/licenses/LICENSE
interpreto-0.4.15.dist-info/METADATA
interpreto-0.4.15.dist-info/WHEEL
interpreto-0.4.15.dist-info/top_level.txt
interpreto-0.4.15.dist-info/RECORD
