Metadata-Version: 2.4
Name: interpreto
Version: 0.4.15
Summary: Interpretability toolbox for LLMs
Author: FOR Team
Author-email: fanny.jourdan@irt-saintexupery.com
Maintainer-email: Fanny Jourdan <fanny.jourdan@irt-saintexupery.com>, Antonin Poché <antonin.poche@irt-saintexupery.com>, Thomas Mullor <thomas.mullor@irt-saintexupery.com>
License: MIT License
Project-URL: homepage, https://github.com/FOR-sight-ai/interpreto
Project-URL: documentation, https://github.com/FOR-sight-ai/interpreto
Project-URL: repository, https://github.com/FOR-sight-ai/interpreto
Project-URL: changelog, https://github.com/FOR-sight-ai/interpreto/blob/main/CHANGELOG.md
Classifier: Development Status :: 3 - Alpha
Classifier: Environment :: Console
Classifier: Environment :: GPU
Classifier: Environment :: GPU :: NVIDIA CUDA
Classifier: Framework :: Jupyter
Classifier: Intended Audience :: Developers
Classifier: Intended Audience :: Science/Research
Classifier: License :: OSI Approved :: Apache Software License
Classifier: Operating System :: OS Independent
Classifier: Programming Language :: Python
Classifier: Programming Language :: Python :: 3
Classifier: Programming Language :: Python :: 3.10
Classifier: Programming Language :: Python :: 3.11
Classifier: Programming Language :: Python :: 3.12
Classifier: Programming Language :: Python :: 3.13
Classifier: Topic :: Scientific/Engineering :: Artificial Intelligence
Classifier: Topic :: Scientific/Engineering :: Visualization
Classifier: Typing :: Typed
Requires-Python: >=3.10
License-File: LICENSE
Requires-Dist: transformers[sentencepiece,tokenizers]>=4.22.0
Requires-Dist: nltk
Requires-Dist: torch>=2.0
Requires-Dist: nnsight>=0.5.1
Requires-Dist: jaxtyping<=0.2.36
Requires-Dist: beartype
Requires-Dist: mknotebooks
Requires-Dist: pymdown-extensions
Requires-Dist: bitsandbytes>=0.48.1
Requires-Dist: scipy
Requires-Dist: matplotlib
Requires-Dist: scikit-learn
Requires-Dist: einops
Requires-Dist: nvidia-cublas-cu11>=11.10.3.66; sys_platform == "Linux"
Requires-Dist: nvidia-cuda-cupti-cu11>=11.7.101; sys_platform == "Linux"
Requires-Dist: nvidia-cuda-nvrtc-cu11>=11.7.99; sys_platform == "Linux"
Requires-Dist: nvidia-cuda-runtime-cu11>=11.7.99; sys_platform == "Linux"
Requires-Dist: nvidia-cudnn-cu11>=8.5.0.96; sys_platform == "Linux"
Requires-Dist: nvidia-cufft-cu11>=10.9.0.58; sys_platform == "Linux"
Requires-Dist: nvidia-curand-cu11>=10.2.10.91; sys_platform == "Linux"
Requires-Dist: nvidia-cusolver-cu11>=11.4.0.1; sys_platform == "Linux"
Requires-Dist: nvidia-cusparse-cu11>=11.7.4.91; sys_platform == "Linux"
Requires-Dist: nvidia-nccl-cu11>=2.14.3; sys_platform == "Linux"
Requires-Dist: nvidia-nvtx-cu11>=11.7.91; sys_platform == "Linux"
Provides-Extra: docs
Requires-Dist: mkdocs>=1.6.1; extra == "docs"
Requires-Dist: mkdocs-material>=9.5.34; extra == "docs"
Requires-Dist: mkdocs-autorefs>=1.1.0; extra == "docs"
Requires-Dist: mkdocs-section-index>=0.3.9; extra == "docs"
Requires-Dist: mkdocstrings>=0.25.2; extra == "docs"
Requires-Dist: mkdocstrings-python>=1.10.9; extra == "docs"
Requires-Dist: mknotebooks>=0.8.0; extra == "docs"
Requires-Dist: docstr-coverage>=2.3.2; extra == "docs"
Provides-Extra: lint
Requires-Dist: setuptools; extra == "lint"
Requires-Dist: pydoclint>=0.4.0; extra == "lint"
Requires-Dist: pre-commit>=2.19.0; extra == "lint"
Requires-Dist: pytest>=7.2.0; extra == "lint"
Requires-Dist: pytest-cov>=4.0.0; extra == "lint"
Requires-Dist: pytest-xdist>=3.5.0; extra == "lint"
Requires-Dist: ruff>=0.2.0; extra == "lint"
Requires-Dist: virtualenv>=20.26.6; extra == "lint"
Requires-Dist: networkx>=3.0.0; extra == "lint"
Requires-Dist: numpy>=2.2.0; extra == "lint"
Provides-Extra: notebook
Requires-Dist: ipykernel>=6.29.2; extra == "notebook"
Requires-Dist: ipywidgets>=8.1.2; extra == "notebook"
Provides-Extra: spacy
Requires-Dist: spacy>=3.8; extra == "spacy"
Requires-Dist: pip; extra == "spacy"
Dynamic: license-file
